Workbook

Sheet Read Me
A1: RBF Platform — SQA Test Suite
A2: Renewable Lesotho RBF Platform · procurement, project lifecycle, verification, payment, administration
A4: Purpose | B4: Complete functional, negative, boundary, security and regression test cases for the platform, written from the application source code (develop/test branch, October 2026).
A5: How to use | B5: 1) Fill the environment block below. 2) Create the accounts on 'Test Accounts & Data'. 3) Execute cases on 'Test Cases' — filter by Module or Priority. 4) Set Status from the dropdown and fill the yellow columns. 5) Log every failure on 'Defect Log' and put its ID in the case's Defect ID column. 6) 'Dashboard' updates automatically.
A6: Suggested order | B6: Run the 'E2E Scenarios' sheet first (smoke), then P1 cases of every module, then P2, then P3.
A7: Priority | B7: P1 = critical path / money / security — must pass for release. P2 = important validation and alternate flows. P3 = edge cases and cosmetic checks.
A8: Type | B8: Positive (happy path) · Negative (invalid input / wrong state) · Boundary (limits) · Security (role & data access) · Regression (recently changed behaviour) · Performance · Compatibility (browsers / devices).
A9: Status values | B9: Not Run · Pass · Fail · Blocked (cannot run because of another defect or missing data) · N/A (not applicable to this release).
A10: Editable cells | B10: Yellow-shaded columns are for the tester: Actual Result, Status, Tested By, Test Date, Defect ID, Remarks. Do not change TC IDs — the dashboard and defect log refer to them.
A11: Expected results | B11: Quoted text in Expected Result is the exact message the application should show. A different wording is a Fail only if the meaning differs — otherwise note it in Remarks.
A12: Known risks | B12: See 'Known Risks' for issues found during code review that testers should confirm (e.g. M3 inclusion targets, session logouts, public /media files).
A13: 'Code review: ... likely FAIL' | B13: Some Expected Results describe the CORRECT behaviour and note that code review suggests the system currently behaves differently. Test them normally: if the system matches the note, mark Fail and log a defect.
A15: Test environment
A16: Application URL
A17: Branch / build
A18: Backend version / commit
A19: Browser(s) & version
A20: Test cycle name
A21: Test lead
A22: Start date
A23: End date

Sheet Dashboard
A1: Test Execution Dashboard
A2: Updates automatically from the Status column on 'Test Cases'.
A4: Module | B4: Total | C4: Pass | D4: Fail | E4: Blocked | F4: N/A | G4: Not Run | H4: Executed % | I4: Pass Rate %
A5: Vendor Registration & Profile | B5: =COUNTIF('Test Cases'!$B$2:$B$3000,$A5) -> 20 | C5: =COUNTIFS('Test Cases'!$B$2:$B$3000,$A5,'Test Cases'!$M$2:$M$3000,"Pass") -> 0 | D5: =COUNTIFS('Test Cases'!$B$2:$B$3000,$A5,'Test Cases'!$M$2:$M$3000,"Fail") -> 0 | E5: =COUNTIFS('Test Cases'!$B$2:$B$3000,$A5,'Test Cases'!$M$2:$M$3000,"Blocked") -> 0 | F5: =COUNTIFS('Test Cases'!$B$2:$B$3000,$A5,'Test Cases'!$M$2:$M$3000,"N/A") -> 0 | G5: =COUNTIFS('Test Cases'!$B$2:$B$3000,$A5,'Test Cases'!$M$2:$M$3000,"Not Run") -> 20 | H5: =IFERROR((B5-G5)/B5,0) -> 0 | I5: =IFERROR(C5/(C5+D5+E5),0) -> 0
A6: Pre-Qualification | B6: =COUNTIF('Test Cases'!$B$2:$B$3000,$A6) -> 16 | C6: =COUNTIFS('Test Cases'!$B$2:$B$3000,$A6,'Test Cases'!$M$2:$M$3000,"Pass") -> 0 | D6: =COUNTIFS('Test Cases'!$B$2:$B$3000,$A6,'Test Cases'!$M$2:$M$3000,"Fail") -> 0 | E6: =COUNTIFS('Test Cases'!$B$2:$B$3000,$A6,'Test Cases'!$M$2:$M$3000,"Blocked") -> 0 | F6: =COUNTIFS('Test Cases'!$B$2:$B$3000,$A6,'Test Cases'!$M$2:$M$3000,"N/A") -> 0 | G6: =COUNTIFS('Test Cases'!$B$2:$B$3000,$A6,'Test Cases'!$M$2:$M$3000,"Not Run") -> 16 | H6: =IFERROR((B6-G6)/B6,0) -> 0 | I6: =IFERROR(C6/(C6+D6+E6),0) -> 0
A7: Tender Management | B7: =COUNTIF('Test Cases'!$B$2:$B$3000,$A7) -> 30 | C7: =COUNTIFS('Test Cases'!$B$2:$B$3000,$A7,'Test Cases'!$M$2:$M$3000,"Pass") -> 0 | D7: =COUNTIFS('Test Cases'!$B$2:$B$3000,$A7,'Test Cases'!$M$2:$M$3000,"Fail") -> 0 | E7: =COUNTIFS('Test Cases'!$B$2:$B$3000,$A7,'Test Cases'!$M$2:$M$3000,"Blocked") -> 0 | F7: =COUNTIFS('Test Cases'!$B$2:$B$3000,$A7,'Test Cases'!$M$2:$M$3000,"N/A") -> 0 | G7: =COUNTIFS('Test Cases'!$B$2:$B$3000,$A7,'Test Cases'!$M$2:$M$3000,"Not Run") -> 30 | H7: =IFERROR((B7-G7)/B7,0) -> 0 | I7: =IFERROR(C7/(C7+D7+E7),0) -> 0
A8: Tender Publish Workflow | B8: =COUNTIF('Test Cases'!$B$2:$B$3000,$A8) -> 12 | C8: =COUNTIFS('Test Cases'!$B$2:$B$3000,$A8,'Test Cases'!$M$2:$M$3000,"Pass") -> 0 | D8: =COUNTIFS('Test Cases'!$B$2:$B$3000,$A8,'Test Cases'!$M$2:$M$3000,"Fail") -> 0 | E8: =COUNTIFS('Test Cases'!$B$2:$B$3000,$A8,'Test Cases'!$M$2:$M$3000,"Blocked") -> 0 | F8: =COUNTIFS('Test Cases'!$B$2:$B$3000,$A8,'Test Cases'!$M$2:$M$3000,"N/A") -> 0 | G8: =COUNTIFS('Test Cases'!$B$2:$B$3000,$A8,'Test Cases'!$M$2:$M$3000,"Not Run") -> 12 | H8: =IFERROR((B8-G8)/B8,0) -> 0 | I8: =IFERROR(C8/(C8+D8+E8),0) -> 0
A9: Notice Board | B9: =COUNTIF('Test Cases'!$B$2:$B$3000,$A9) -> 6 | C9: =COUNTIFS('Test Cases'!$B$2:$B$3000,$A9,'Test Cases'!$M$2:$M$3000,"Pass") -> 0 | D9: =COUNTIFS('Test Cases'!$B$2:$B$3000,$A9,'Test Cases'!$M$2:$M$3000,"Fail") -> 0 | E9: =COUNTIFS('Test Cases'!$B$2:$B$3000,$A9,'Test Cases'!$M$2:$M$3000,"Blocked") -> 0 | F9: =COUNTIFS('Test Cases'!$B$2:$B$3000,$A9,'Test Cases'!$M$2:$M$3000,"N/A") -> 0 | G9: =COUNTIFS('Test Cases'!$B$2:$B$3000,$A9,'Test Cases'!$M$2:$M$3000,"Not Run") -> 6 | H9: =IFERROR((B9-G9)/B9,0) -> 0 | I9: =IFERROR(C9/(C9+D9+E9),0) -> 0
A10: EOI Invites | B10: =COUNTIF('Test Cases'!$B$2:$B$3000,$A10) -> 11 | C10: =COUNTIFS('Test Cases'!$B$2:$B$3000,$A10,'Test Cases'!$M$2:$M$3000,"Pass") -> 0 | D10: =COUNTIFS('Test Cases'!$B$2:$B$3000,$A10,'Test Cases'!$M$2:$M$3000,"Fail") -> 0 | E10: =COUNTIFS('Test Cases'!$B$2:$B$3000,$A10,'Test Cases'!$M$2:$M$3000,"Blocked") -> 0 | F10: =COUNTIFS('Test Cases'!$B$2:$B$3000,$A10,'Test Cases'!$M$2:$M$3000,"N/A") -> 0 | G10: =COUNTIFS('Test Cases'!$B$2:$B$3000,$A10,'Test Cases'!$M$2:$M$3000,"Not Run") -> 11 | H10: =IFERROR((B10-G10)/B10,0) -> 0 | I10: =IFERROR(C10/(C10+D10+E10),0) -> 0
A11: Bids | B11: =COUNTIF('Test Cases'!$B$2:$B$3000,$A11) -> 21 | C11: =COUNTIFS('Test Cases'!$B$2:$B$3000,$A11,'Test Cases'!$M$2:$M$3000,"Pass") -> 0 | D11: =COUNTIFS('Test Cases'!$B$2:$B$3000,$A11,'Test Cases'!$M$2:$M$3000,"Fail") -> 0 | E11: =COUNTIFS('Test Cases'!$B$2:$B$3000,$A11,'Test Cases'!$M$2:$M$3000,"Blocked") -> 0 | F11: =COUNTIFS('Test Cases'!$B$2:$B$3000,$A11,'Test Cases'!$M$2:$M$3000,"N/A") -> 0 | G11: =COUNTIFS('Test Cases'!$B$2:$B$3000,$A11,'Test Cases'!$M$2:$M$3000,"Not Run") -> 21 | H11: =IFERROR((B11-G11)/B11,0) -> 0 | I11: =IFERROR(C11/(C11+D11+E11),0) -> 0
A12: Bid Evaluation | B12: =COUNTIF('Test Cases'!$B$2:$B$3000,$A12) -> 21 | C12: =COUNTIFS('Test Cases'!$B$2:$B$3000,$A12,'Test Cases'!$M$2:$M$3000,"Pass") -> 0 | D12: =COUNTIFS('Test Cases'!$B$2:$B$3000,$A12,'Test Cases'!$M$2:$M$3000,"Fail") -> 0 | E12: =COUNTIFS('Test Cases'!$B$2:$B$3000,$A12,'Test Cases'!$M$2:$M$3000,"Blocked") -> 0 | F12: =COUNTIFS('Test Cases'!$B$2:$B$3000,$A12,'Test Cases'!$M$2:$M$3000,"N/A") -> 0 | G12: =COUNTIFS('Test Cases'!$B$2:$B$3000,$A12,'Test Cases'!$M$2:$M$3000,"Not Run") -> 21 | H12: =IFERROR((B12-G12)/B12,0) -> 0 | I12: =IFERROR(C12/(C12+D12+E12),0) -> 0
A13: Award & Standstill | B13: =COUNTIF('Test Cases'!$B$2:$B$3000,$A13) -> 18 | C13: =COUNTIFS('Test Cases'!$B$2:$B$3000,$A13,'Test Cases'!$M$2:$M$3000,"Pass") -> 0 | D13: =COUNTIFS('Test Cases'!$B$2:$B$3000,$A13,'Test Cases'!$M$2:$M$3000,"Fail") -> 0 | E13: =COUNTIFS('Test Cases'!$B$2:$B$3000,$A13,'Test Cases'!$M$2:$M$3000,"Blocked") -> 0 | F13: =COUNTIFS('Test Cases'!$B$2:$B$3000,$A13,'Test Cases'!$M$2:$M$3000,"N/A") -> 0 | G13: =COUNTIFS('Test Cases'!$B$2:$B$3000,$A13,'Test Cases'!$M$2:$M$3000,"Not Run") -> 18 | H13: =IFERROR((B13-G13)/B13,0) -> 0 | I13: =IFERROR(C13/(C13+D13+E13),0) -> 0
A14: Blacklisting | B14: =COUNTIF('Test Cases'!$B$2:$B$3000,$A14) -> 11 | C14: =COUNTIFS('Test Cases'!$B$2:$B$3000,$A14,'Test Cases'!$M$2:$M$3000,"Pass") -> 0 | D14: =COUNTIFS('Test Cases'!$B$2:$B$3000,$A14,'Test Cases'!$M$2:$M$3000,"Fail") -> 0 | E14: =COUNTIFS('Test Cases'!$B$2:$B$3000,$A14,'Test Cases'!$M$2:$M$3000,"Blocked") -> 0 | F14: =COUNTIFS('Test Cases'!$B$2:$B$3000,$A14,'Test Cases'!$M$2:$M$3000,"N/A") -> 0 | G14: =COUNTIFS('Test Cases'!$B$2:$B$3000,$A14,'Test Cases'!$M$2:$M$3000,"Not Run") -> 11 | H14: =IFERROR((B14-G14)/B14,0) -> 0 | I14: =IFERROR(C14/(C14+D14+E14),0) -> 0
A15: Contract (PBA) | B15: =COUNTIF('Test Cases'!$B$2:$B$3000,$A15) -> 11 | C15: =COUNTIFS('Test Cases'!$B$2:$B$3000,$A15,'Test Cases'!$M$2:$M$3000,"Pass") -> 0 | D15: =COUNTIFS('Test Cases'!$B$2:$B$3000,$A15,'Test Cases'!$M$2:$M$3000,"Fail") -> 0 | E15: =COUNTIFS('Test Cases'!$B$2:$B$3000,$A15,'Test Cases'!$M$2:$M$3000,"Blocked") -> 0 | F15: =COUNTIFS('Test Cases'!$B$2:$B$3000,$A15,'Test Cases'!$M$2:$M$3000,"N/A") -> 0 | G15: =COUNTIFS('Test Cases'!$B$2:$B$3000,$A15,'Test Cases'!$M$2:$M$3000,"Not Run") -> 11 | H15: =IFERROR((B15-G15)/B15,0) -> 0 | I15: =IFERROR(C15/(C15+D15+E15),0) -> 0
A16: Project Assignment & Milestones | B16: =COUNTIF('Test Cases'!$B$2:$B$3000,$A16) -> 14 | C16: =COUNTIFS('Test Cases'!$B$2:$B$3000,$A16,'Test Cases'!$M$2:$M$3000,"Pass") -> 0 | D16: =COUNTIFS('Test Cases'!$B$2:$B$3000,$A16,'Test Cases'!$M$2:$M$3000,"Fail") -> 0 | E16: =COUNTIFS('Test Cases'!$B$2:$B$3000,$A16,'Test Cases'!$M$2:$M$3000,"Blocked") -> 0 | F16: =COUNTIFS('Test Cases'!$B$2:$B$3000,$A16,'Test Cases'!$M$2:$M$3000,"N/A") -> 0 | G16: =COUNTIFS('Test Cases'!$B$2:$B$3000,$A16,'Test Cases'!$M$2:$M$3000,"Not Run") -> 14 | H16: =IFERROR((B16-G16)/B16,0) -> 0 | I16: =IFERROR(C16/(C16+D16+E16),0) -> 0
... A39: Uploads & Non-Functional | B39: =COUNTIF('Test Cases'!$B$2:$B$3000,$A39) -> 13 | C39: =COUNTIFS('Test Cases'!$B$2:$B$3000,$A39,'Test Cases'!$M$2:$M$3000,"Pass") -> 0 | D39: =COUNTIFS('Test Cases'!$B$2:$B$3000,$A39,'Test Cases'!$M$2:$M$3000,"Fail") -> 0 | E39: =COUNTIFS('Test Cases'!$B$2:$B$3000,$A39,'Test Cases'!$M$2:$M$3000,"Blocked") -> 0 | F39: =COUNTIFS('Test Cases'!$B$2:$B$3000,$A39,'Test Cases'!$M$2:$M$3000,"N/A") -> 0 | G39: =COUNTIFS('Test Cases'!$B$2:$B$3000,$A39,'Test Cases'!$M$2:$M$3000,"Not Run") -> 13 | H39: =IFERROR((B39-G39)/B39,0) -> 0 | I39: =IFERROR(C39/(C39+D39+E39),0) -> 0
A40: TOTAL | B40: =SUM(B5:B39) -> 463 | C40: =SUM(C5:C39) -> 0 | D40: =SUM(D5:D39) -> 0 | E40: =SUM(E5:E39) -> 0 | F40: =SUM(F5:F39) -> 0 | G40: =SUM(G5:G39) -> 463 | H40: =IFERROR((B40-G40)/B40,0) -> 0 | I40: =IFERROR(C40/(C40+D40+E40),0) -> 0
A43: By priority
A44: Priority | B44: Total | C44: Pass | D44: Fail | E44: Blocked | F44: N/A | G44: Not Run | H44: Executed % | I44: Pass Rate %
A45: P1 | B45: =COUNTIF('Test Cases'!$F$2:$F$3000,$A45) -> 171 | C45: =COUNTIFS('Test Cases'!$F$2:$F$3000,$A45,'Test Cases'!$M$2:$M$3000,"Pass") -> 0 | D45: =COUNTIFS('Test Cases'!$F$2:$F$3000,$A45,'Test Cases'!$M$2:$M$3000,"Fail") -> 0 | E45: =COUNTIFS('Test Cases'!$F$2:$F$3000,$A45,'Test Cases'!$M$2:$M$3000,"Blocked") -> 0 | F45: =COUNTIFS('Test Cases'!$F$2:$F$3000,$A45,'Test Cases'!$M$2:$M$3000,"N/A") -> 0 | G45: =COUNTIFS('Test Cases'!$F$2:$F$3000,$A45,'Test Cases'!$M$2:$M$3000,"Not Run") -> 171 | H45: =IFERROR((B45-G45)/B45,0) -> 0 | I45: =IFERROR(C45/(C45+D45+E45),0) -> 0
A46: P2 | B46: =COUNTIF('Test Cases'!$F$2:$F$3000,$A46) -> 176 | C46: =COUNTIFS('Test Cases'!$F$2:$F$3000,$A46,'Test Cases'!$M$2:$M$3000,"Pass") -> 0 | D46: =COUNTIFS('Test Cases'!$F$2:$F$3000,$A46,'Test Cases'!$M$2:$M$3000,"Fail") -> 0 | E46: =COUNTIFS('Test Cases'!$F$2:$F$3000,$A46,'Test Cases'!$M$2:$M$3000,"Blocked") -> 0 | F46: =COUNTIFS('Test Cases'!$F$2:$F$3000,$A46,'Test Cases'!$M$2:$M$3000,"N/A") -> 0 | G46: =COUNTIFS('Test Cases'!$F$2:$F$3000,$A46,'Test Cases'!$M$2:$M$3000,"Not Run") -> 176 | H46: =IFERROR((B46-G46)/B46,0) -> 0 | I46: =IFERROR(C46/(C46+D46+E46),0) -> 0
A47: P3 | B47: =COUNTIF('Test Cases'!$F$2:$F$3000,$A47) -> 116 | C47: =COUNTIFS('Test Cases'!$F$2:$F$3000,$A47,'Test Cases'!$M$2:$M$3000,"Pass") -> 0 | D47: =COUNTIFS('Test Cases'!$F$2:$F$3000,$A47,'Test Cases'!$M$2:$M$3000,"Fail") -> 0 | E47: =COUNTIFS('Test Cases'!$F$2:$F$3000,$A47,'Test Cases'!$M$2:$M$3000,"Blocked") -> 0 | F47: =COUNTIFS('Test Cases'!$F$2:$F$3000,$A47,'Test Cases'!$M$2:$M$3000,"N/A") -> 0 | G47: =COUNTIFS('Test Cases'!$F$2:$F$3000,$A47,'Test Cases'!$M$2:$M$3000,"Not Run") -> 116 | H47: =IFERROR((B47-G47)/B47,0) -> 0 | I47: =IFERROR(C47/(C47+D47+E47),0) -> 0
A50: Release gate
A51: Open P1 failures | B51: =COUNTIFS('Test Cases'!$F$2:$F$3000,"P1",'Test Cases'!$M$2:$M$3000,"Fail") -> 0
A52: Open defects (Defect Log) | B52: =COUNTIFS('Defect Log'!$I$3:$I$2000,"<>Closed",'Defect Log'!$A$3:$A$2000,"<>") -> 1 | C52: Includes the example row on 'Defect Log' until it is deleted.
A53: Ready for release? | B53: =IF(AND(B51=0,D40=0,G40=0),"YES","NO") -> NO
A54: Rule: no P1 failures, no failed cases, and every case executed.

Sheet Test Cases
A1: TC ID | B1: Module | C1: Sub-module | D1: Test Title | E1: Role | F1: Priority | G1: Type | H1: Preconditions | I1: Test Steps | J1: Test Data | K1: Expected Result | L1: Actual Result | M1: Status | N1: Tested By | O1: Test Date | P1: Defect ID | Q1: Remarks
A2: REG-001 | B2: Vendor Registration & Profile | C2: Registration | D2: Vendor registers through the 3-step wizard | E2: Anonymous | F2: P1 | G2: Positive | H2: SMTP configured (or DEBUG for debug OTP) | I2: 1. Open registration 2. Step 1 'Register your organisation' -> 'Continue' 3. Step 2 'Organisation details' -> 'Send verification code' 4. Step 3 enter 6-digit OTP -> 'Verify & create account' | J2: Unique email, username, Tax ID, registration no.; mobile 58123456; certificate PDF 1 MB; consent ticked | K2: Account created with status Pending; can log in | M2: Not Run
A3: REG-002 | B3: Vendor Registration & Profile | C3: OTP | D3: OTP resend cooldown 60 s | E3: Anonymous | F3: P2 | G3: Boundary | H3: OTP just requested | I3: 1. Request another code within 60 s | J3: — | K3: HTTP 429 'Please wait 60 seconds before requesting another code.' | M3: Not Run
A4: REG-003 | B4: Vendor Registration & Profile | C4: OTP | D4: OTP request limit per network | E4: Anonymous | F4: P3 | G4: Security | H4: — | I4: 1. Request 11 codes from same IP within an hour (respecting cooldown) | J4: — | K4: 11th: 'Too many verification codes requested from this network. Try again later.' | M4: Not Run
A5: REG-004 | B5: Vendor Registration & Profile | C5: OTP | D5: Wrong OTP attempts | E5: Anonymous | F5: P1 | G5: Security | H5: OTP requested | I5: 1. Enter wrong code 1-4 times 2. Enter wrong code 5th time | J5: — | K5: 'Incorrect code. N attempt(s) remaining.'; 5th: 'Too many incorrect codes. Request a new verification code.' | M5: Not Run
A6: REG-005 | B6: Vendor Registration & Profile | C6: OTP | D6: Expired OTP | E6: Anonymous | F6: P2 | G6: Boundary | H6: OTP older than 10 minutes | I6: 1. Enter the code | J6: — | K6: 'OTP has expired. Please request a new one.' | M6: Not Run
A7: REG-006 | B7: Vendor Registration & Profile | C7: OTP | D7: No SMTP in production | E7: Anonymous | F7: P3 | G7: Negative | H7: Production, SMTP not configured | I7: 1. Request OTP | J7: — | K7: 503 'Email service is not configured.' | M7: Not Run
A8: REG-007 | B8: Vendor Registration & Profile | C8: Validation | D8: Duplicate email / username / Tax ID / registration no. | E8: Anonymous | F8: P1 | G8: Negative | H8: Existing vendor | I8: 1. Register re-using each value in turn | J8: — | K8: 'An account with this email already exists...', 'This username is already taken.', 'A vendor with this Tax ID is already registered...', 'A vendor with this registration number is already registered.' | M8: Not Run
A9: REG-008 | B9: Vendor Registration & Profile | C9: Validation | D9: Registration certificate rules | E9: Anonymous | F9: P2 | G9: Negative | H9: — | I9: 1. Submit without certificate 2. Upload .docx 3. Upload 11 MB PDF 4. Upload a .txt renamed .pdf | J9: — | K9: 'Upload your company registration certificate (PDF, JPG or PNG).' / '...must be one of: JPG, PDF, PNG.' / '...larger than the 10 MB limit.' / '...does not look like a valid PDF file.' | M9: Not Run
A10: REG-009 | B10: Vendor Registration & Profile | C10: Validation | D10: Lesotho mobile number formats | E10: Anonymous | F10: P2 | G10: Boundary | H10: — | I10: 1. Enter 48123456 2. Enter 2665812345 (10 digits) 3. Enter 26658123456 4. Enter +27821234567 | J10: — | K10: 48..: 'Enter a Lesotho mobile number starting with 5 or 6...'; 10-digit 266: 'A Lesotho mobile number is +266 followed by 8 digits...'; valid ones accepted | M10: Not Run
A11: REG-010 | B11: Vendor Registration & Profile | C11: Validation | D11: Password rules | E11: Anonymous | F11: P2 | G11: Negative | H11: — | I11: 1. Password 'abc123' 2. Password '12345678' 3. Password 'password' 4. Passwords not matching | J11: — | K11: Rejected for length, all-numeric, common password; 'Passwords do not match.' | M11: Not Run
A12: REG-011 | B12: Vendor Registration & Profile | C12: Validation | D12: Username client rules | E12: Anonymous | F12: P3 | G12: Boundary | H12: — | I12: 1. Username 'ab' 2. Username 'bad name!' | J12: — | K12: 'Username must be at least 3 characters.' / 'Use only letters, numbers and @ . + - _' | M12: Not Run
A13: REG-012 | B13: Vendor Registration & Profile | C13: Validation | D13: Consent required | E13: Anonymous | F13: P2 | G13: Negative | H13: — | I13: 1. Untick terms consent 2. Submit | J13: — | K13: 'You must accept the terms and privacy notice to register.' | M13: Not Run
... A464: NFR-013 | B464: Uploads & Non-Functional | C464: Security | D464: API docs exposure | E464: Anonymous | F464: P3 | G464: Security | H464: — | I464: 1. Open /api/docs/ in production | J464: — | K464: Not publicly accessible (decide with team) | M464: Not Run

Sheet E2E Scenarios
A1: Scenario ID | B1: Scenario | C1: Goal | D1: Flow (roles in order) | E1: Covers TC IDs | F1: Status | G1: Tested By | H1: Test Date | I1: Defect ID | J1: Notes
A2: E2E-01 | B2: Procurement — registration to awarded contract | C2: Prove a new vendor can register, pre-qualify, bid, be evaluated and be awarded, producing a PBA contract. | D2: 1. Vendor: register (OTP) and submit pre-qualification 2. RMT: start review -> approve 3. RMT: create tender (EOI -> Combined) -> Verify -> Request Publish Approval 4. Super Admin: approve publication 5. RMT: Publish (vendors notified) 6. Vendor: submit EOI 7. RMT: shortlist EOI 8. Vendor: submit final combined proposal 9. Super Admin: assign 3-member Evaluation Committee 10. EC members: attest COI, score technical, Submit & Lock 11. RMT: Open Financial Stage 12. EC: finalize financial scores; suggest the same winner 13. RMT: request Intent to Award 14. Super Admin: Approve & Issue (standstill starts) 15. RMT: after cooling-off, Confirm Final Award 16. Vendor: 'Performance-Based Agreement Ready' -> continue with E2E-03 | E2: REG-001 · PQ-001,009 · TND-001 · PUB-001,002,005,009 · EOI-001,003,007 · BID-001 · EVL-001,004,007,013,015,017 · AWD-001,005,015 | F2: Not Run
A3: E2E-02 | B3: Award challenge during standstill | C3: Prove a losing bidder can challenge and the award pauses until RMT resolves it. | D3: 1. Reach Standstill (E2E-01 up to intent approval) with 2 bidders 2. Losing vendor: 'Challenge Award Decision' 3. Tender shows Disputed; Confirm Final Award blocked 4. RMT: dismiss challenge -> Standstill resumes 5. Repeat with a new challenge -> uphold -> new intent request for challenger 6. Super Admin approves; confirm after cooling-off | E3: AWD-008,010,012,016 | F3: Not Run
A4: E2E-03 | B4: Happy path — full lifecycle with default 0/50/50 split | C4: Prove a project can go from approved contract to Completed with every role acting once. | D4: 1. RMT: generate PBA 2. Vendor: upload signed PDF 3. RMT: approve contract; assign project (0/50/50, target 5) 4. Vendor: submit setup 5. RMT: Start Review -> Approve Setup 6. RMT: M1 'Verify & proceed' (M1 is 0%, no claim) 7. Vendor: submit 4 installations + meter CSV 8. Field Verifier: verify all 4 9. DoE: acknowledge verifications 10. RMT: verify meter batch 11. Vendor: submit M2 claim 12. RMT approve -> TAC endorse -> PSC approve -> RMT Confirm Payment 13. RMT: M2 'Verify & proceed' 14. Vendor: 5th installation; Field Verifier verifies 15. Vendor: submit M3 claim 16. RMT -> TAC -> PSC -> RMT Confirm Payment 17. RMT: 'Verify & complete project' | E4: CON-001,004,008 · ASG-001 · SET-002,012,013 · MS-001,003,008 · INS-001 · FV-001 · DOE-001 · MTR-001,005 · CLM-001 · APR-001,009,012,017 · MCR-001,005 | F4: Not Run
A5: E2E-04 | B5: Partial payment and carry-over | C5: Prove a partial M2 payment carries the shortfall into M3 and settles on payment. | D5: 1. Reach M2 claimable with 85% verified (M2 requirement lowered to 80%) 2. RMT: Approve partially at 85% with deficiencies 3. TAC endorse, PSC approve, RMT confirm payment 4. Check 'Milestone Shortfall Carried Over' activity 5. Reach M3, submit claim 6. Check M3 claim amount = M3 amount + shortfall 7. Complete M3 payment; carry-over shown Settled | E5: APR-002,003,005,022 · CLM-002 | F5: Not Run
A6: E2E-05 | B6: Every send-back path | C6: Prove each reviewer can send work back and the submitter can recover. | D6: 1. RMT: reject contract -> Vendor re-uploads 2. RMT: request setup changes -> Vendor resubmits 3. Field Verifier: flag installation -> Vendor Fix & Resubmit -> re-verify 4. DoE: request re-verification -> Verifier re-verifies 5. RMT: return claim for completion -> Vendor resubmits 6. TAC: push back to RMT -> RMT approves again 7. PSC: reject claim -> Vendor files new claim -> full chain | E6: CON-009 · SET-014,017 · FV-012 · DOE-004 · APR-007,010,013 · CLM-007 | F6: Not Run
A7: E2E-06 | B7: Payment holds | C7: Prove oversight, anomaly and audit findings stop payment until resolved. | D7: 1. Claim at RMT Approved 2. PSC: Flagged review with 'Hold milestone payments' 3. TAC: endorse blocked (409, button disabled) 4. RMT: resolve follow-up -> TAC endorse works 5. Auditor: open audit case on claim -> PSC approve blocked 6. Close audit case -> PSC approve works 7. Escalated anomaly -> confirm payment blocked -> resolve -> works | E7: OVS-002,003 · AUC-005 · APR-025 · ANM-007 | F7: Not Run
A8: E2E-07 | B8: Close project early at M1 | C8: Prove RMT can stop a project at the 0% mobilization milestone. | D8: 1. Assign project with default split 2. Approve setup 3. RMT: M1 completion review -> 'Close project' with notes 4. Check project Closed, M2 and M3 Cancelled, vendor notified | E8: MS-005 | F8: Not Run
A9: E2E-08 | B9: Transfer to another vendor | C9: Prove remaining milestones move to a new vendor after a paid milestone. | D9: 1. Complete and pay M2 2. RMT: 'Verify & transfer to another vendor' -> pick vendor B 3. Vendor B: sees project, notified 'Project Transferred To You' 4. Vendor A: no longer can submit for the project | E9: MCR-002,003 | F9: Not Run
A10: E2E-09 | B10: Blacklisting halts a project | C10: Prove a blacklisted vendor's project and payments are frozen. | D10: 1. Project Active with claim in chain 2. Super Admin: blacklist the vendor 3. Project shows Halted; claims Held/Audit 4. Vendor: claim submission blocked 5. Field Verifier: verification paused | E10: BLK-003,006 · CLM-006 · FV-010 | F10: Not Run
A11: E2E-10 | B11: Long session stability | C11: Prove no intermittent 500s or forced logouts during a working day. | D11: 1. Log in as RMT 2. Work for 2 hours with actions every few minutes, including a 25-minute pause 3. Open two tabs; idle one 4. Record every 500 / logout with time and network trace | E11: SES-001..006 | F11: Not Run

Sheet Test Accounts & Data
A1: Role (as in app) | B1: Needed for | C1: Required setup | D1: Username (fill in) | E1: Password / notes (fill in)
A2: Platform Administrator (Super Admin) | B2: Platform Configuration, users, inclusion targets, blacklisting, budget | C2: Inclusion targets totalling <= 100% for M3 tests; national budget set
A3: RBF Management Team (RMT) | B3: Contract, assignment, setup review, meter/anomaly review, claim approval, payment, milestone decisions | C3: —
A4: Vendor A | B4: Bidding, contract, setup, installations, claims | C4: Pre-qualified; owns an Awarded bid; bank details on profile
A5: Vendor B | B5: Security tests (cross-vendor) and project transfer | C5: Pre-qualified, active, not blacklisted
A6: Field Verifier | B6: Field verification | C6: verification_zone = the project district
A7: Field Verifier (other district) | B7: Security test: district restriction | C7: verification_zone = a different district
A8: DoE Officer | B8: Acknowledge / re-verify, site visits, KPI reviews | C8: Region includes the project district
A9: DoE Officer (other region) | B9: Security test: region restriction | C9: Region excludes the project district
A10: TAC Member | B10: Claim endorsement | C10: —
A11: Project Steering Committee (PSC) | B11: Final claim approval, oversight, holds | C11: —
A12: Auditor | B12: Audit cases and holds | C12: —
A13: Evaluation Committee member(s) | B13: Bid evaluation | C13: Assigned to the tender's evaluation
A16: Test data to prepare
A17: Item | B17: Rule enforced by the system | C17: Prepared? (Y/N)
A18: Signed contract | B18: PDF only, max 10 MB (prepare 2 MB valid, 10.5 MB invalid, a .docx)
A19: Setup documents | B19: PDF or DOCX, max 5 MB each: team roster, equipment plan, compliance docs, insurance certificate
A20: Device brand / model | B20: Must exactly match the awarded bid
A21: Installation GPS points | B21: Inside Lesotho and inside the project district; > 10 m apart; one point outside Lesotho and one in another district for negative tests
A22: Verifier GPS | B22: Within 50 m of the vendor point (and one at ~60 m for the mismatch test)
A23: Serial numbers / Beneficiary IDs | B23: Unique programme-wide; reuse one for duplicate tests
A24: Photos | B24: jpg/png, <= 5 MB, up to 5 per installation; one 6 MB file for limit tests
A25: Meter CSV | B25: CSV <= 5 MB; meter_id/installation_id must match the project's installations; readings dated within 30 days
A26: Bank reference | B26: Any string, e.g. IFMS-2026-00123

Sheet Defect Log
A1: Defect Log — one row per defect. Row 3 is an example; overwrite or delete it.
A2: Defect ID | B2: TC ID | C2: Title | D2: Module | E2: Severity | F2: Steps to reproduce | G2: Expected | H2: Actual (attach screenshot / network log) | I2: Status | J2: Reported By | K2: Reported Date | L2: Assigned To | M2: Fixed In Build | N2: Retest Result
A3: DEF-001 | B3: SES-001 | C3: 403 'token_not_valid' after 30 minutes logs user out | D3: Session & Reliability | E3: High | F3: 1. Log in as RMT 2. Work continuously for 31 minutes 3. Approve a claim | G3: Claim approved after silent token refresh | H3: HTTP 403 token_not_valid; redirected to login on reload | I3: Open | J3: QA name | K3: 2026-10-12 | L3: Backend team

Sheet Known Risks
A1: # | B1: Area | C1: Risk found in code review | D1: How to confirm | E1: Related TC | F1: Confirmed? (Y/N) | G1: Notes
A2: 1 | B2: Security | C2: Uploaded files under /media/ are served without authentication — IDs, certificates and bank documents are downloadable by anyone with the URL. | D2: Open a /media/ file URL in a private window. | E2: RBAC-009
A3: 2 | B3: Security | C3: No login lockout or throttling; unlimited password guesses. | D3: Run AUTH-006. | E3: AUTH-006
A4: 3 | B4: Security | C4: Forced first-login password change is enforced only in the UI; the API works with the token. | D4: Run AUTH-011. | E4: AUTH-011
A5: 4 | B5: Security | C5: Logout and password resets do not revoke tokens (refresh valid 7 days). | D5: Run AUTH-020. | E5: AUTH-020
A6: 5 | B6: Security | C6: Any role can open the GIS map via a typed URL and see beneficiary data. | D6: Run RBAC-002. | E6: RBAC-002
A7: 6 | B7: Procurement | C7: RMT can PATCH a tender's status to Published, bypassing verification, Super Admin approval and notifications. | D7: Run TND-014. | E7: TND-014
A8: 7 | B8: Procurement | C8: Publishing with no approved vendors (or email failure) returns an error but the tender is already Published. | D8: Run PUB-011. | E8: PUB-011
A9: 8 | B9: Procurement | C9: Award challenges accept a client-supplied vendor id, so anyone can file in another vendor's name. | D9: Run AWD-009. | E9: AWD-009
A10: 9 | B10: Procurement | C10: 'Edit Submission Timeline' sends identical stage deadlines and is likely always rejected. | D10: Run TND-018. | E10: TND-018
A11: 10 | B11: Blacklisting | C11: Rejecting a confirmed blacklist reactivates the vendor while projects stay Halted; reinstatement does not block bidding; temporary blacklists never expire automatically. | D11: Run BLK-008, BLK-009. | E11: BLK-008
A12: 11 | B12: Milestones / KPIs | C12: Default inclusion targets 50% female-headed + 30% vulnerable + 60% low-income = 140%. Each installation has one household type, so Milestone 3 can never become claimable with defaults. | D12: Run MS-014 with default targets; try every household mix. | E12: MS-014
A13: 12 | B13: Session | C13: Expired access token returns HTTP 403 (not 401) because SessionAuthentication is listed first; the frontend refreshes only on 401, so users see errors after ~30 min and are sent to login on reload. | D13: Stay active > 30 min, perform CRUD, watch the network tab for 403 token_not_valid. | E13: SES-001
... A19: 18 | B19: Installations | C19: If no Field Verifier covers a district, installations stay Submitted with no warning. | D19: Run INS-018. | E19: INS-018
